num_primos/__init__.py
num_primos_py-1.0.dist-info/LICENSE
num_primos_py-1.0.dist-info/METADATA
num_primos_py-1.0.dist-info/WHEEL
num_primos_py-1.0.dist-info/top_level.txt
num_primos_py-1.0.dist-info/RECORD
