Metadata-Version: 2.1
Name: num-primos-py
Version: 1.0
Summary: A function to calculate prime numbers.
Home-page: UNKNOWN
Author: Kevin Almendarez
Author-email: kevinem986@hotmail.com
License: GNU GPLv3
Keywords: mathematical operations
Platform: UNKNOWN
Classifier: Development Status :: 4 - Beta
Classifier: Intended Audience :: Developers
Classifier: Topic :: Utilities
Classifier: License :: OSI Approved :: GNU General Public License v3 (GPLv3)
Classifier: Programming Language :: Python :: 3
Classifier: Operating System :: OS Independent
License-File: LICENSE
